{
	"id": "845ab93f7941ad2cb373f86d24597f78",
	"_format": "hh-sol-build-info-1",
	"solcVersion": "0.8.23",
	"solcLongVersion": "0.8.23+commit.f704f362",
	"input": {
		"language": "Solidity",
		"settings": {
			"optimizer": {
				"enabled": true,
				"runs": 200
			},
			"viaIR": true,
			"outputSelection": {
				"*": {
					"*": [
						"evm.bytecode",
						"evm.deployedBytecode",
						"devdoc",
						"userdoc",
						"metadata",
						"abi"
					]
				}
			},
			"remappings": []
		},
		"sources": {
			"contracts/access_token/draft-IERC6093.sol": {
				"content": "// SPDX-License-Identifier: MIT\n// OpenZeppelin Contracts (last updated v5.0.0) (interfaces/draft-IERC6093.sol)\npragma solidity ^0.8.20;\n\n/**\n * @dev Standard ERC20 Errors\n * Interface of the https://eips.ethereum.org/EIPS/eip-6093[ERC-6093] custom errors for ERC20 tokens.\n */\ninterface IERC20Errors {\n    /**\n     * @dev Indicates an error related to the current `balance` of a `sender`. Used in transfers.\n     * @param sender Address whose tokens are being transferred.\n     * @param balance Current balance for the interacting account.\n     * @param needed Minimum amount required to perform a transfer.\n     */\n    error ERC20InsufficientBalance(address sender, uint256 balance, uint256 needed);\n\n    /**\n     * @dev Indicates a failure with the token `sender`. Used in transfers.\n     * @param sender Address whose tokens are being transferred.\n     */\n    error ERC20InvalidSender(address sender);\n\n    /**\n     * @dev Indicates a failure with the token `receiver`. Used in transfers.\n     * @param receiver Address to which tokens are being transferred.\n     */\n    error ERC20InvalidReceiver(address receiver);\n\n    /**\n     * @dev Indicates a failure with the `spender`’s `allowance`. Used in transfers.\n     * @param spender Address that may be allowed to operate on tokens without being their owner.\n     * @param allowance Amount of tokens a `spender` is allowed to operate with.\n     * @param needed Minimum amount required to perform a transfer.\n     */\n    error ERC20InsufficientAllowance(address spender, uint256 allowance, uint256 needed);\n\n    /**\n     * @dev Indicates a failure with the `approver` of a token to be approved. Used in approvals.\n     * @param approver Address initiating an approval operation.\n     */\n    error ERC20InvalidApprover(address approver);\n\n    /**\n     * @dev Indicates a failure with the `spender` to be approved. Used in approvals.\n     * @param spender Address that may be allowed to operate on tokens without being their owner.\n     */\n    error ERC20InvalidSpender(address spender);\n}\n\n/**\n * @dev Standard ERC721 Errors\n * Interface of the https://eips.ethereum.org/EIPS/eip-6093[ERC-6093] custom errors for ERC721 tokens.\n */\ninterface IERC721Errors {\n    /**\n     * @dev Indicates that an address can't be an owner. For example, `address(0)` is a forbidden owner in EIP-20.\n     * Used in balance queries.\n     * @param owner Address of the current owner of a token.\n     */\n    error ERC721InvalidOwner(address owner);\n\n    /**\n     * @dev Indicates a `tokenId` whose `owner` is the zero address.\n     * @param tokenId Identifier number of a token.\n     */\n    error ERC721NonexistentToken(uint256 tokenId);\n\n    /**\n     * @dev Indicates an error related to the ownership over a particular token. Used in transfers.\n     * @param sender Address whose tokens are being transferred.\n     * @param tokenId Identifier number of a token.\n     * @param owner Address of the current owner of a token.\n     */\n    error ERC721IncorrectOwner(address sender, uint256 tokenId, address owner);\n\n    /**\n     * @dev Indicates a failure with the token `sender`. Used in transfers.\n     * @param sender Address whose tokens are being transferred.\n     */\n    error ERC721InvalidSender(address sender);\n\n    /**\n     * @dev Indicates a failure with the token `receiver`. Used in transfers.\n     * @param receiver Address to which tokens are being transferred.\n     */\n    error ERC721InvalidReceiver(address receiver);\n\n    /**\n     * @dev Indicates a failure with the `operator`’s approval. Used in transfers.\n     * @param operator Address that may be allowed to operate on tokens without being their owner.\n     * @param tokenId Identifier number of a token.\n     */\n    error ERC721InsufficientApproval(address operator, uint256 tokenId);\n\n    /**\n     * @dev Indicates a failure with the `approver` of a token to be approved. Used in approvals.\n     * @param approver Address initiating an approval operation.\n     */\n    error ERC721InvalidApprover(address approver);\n\n    /**\n     * @dev Indicates a failure with the `operator` to be approved. Used in approvals.\n     * @param operator Address that may be allowed to operate on tokens without being their owner.\n     */\n    error ERC721InvalidOperator(address operator);\n}\n\n/**\n * @dev Standard ERC1155 Errors\n * Interface of the https://eips.ethereum.org/EIPS/eip-6093[ERC-6093] custom errors for ERC1155 tokens.\n */\ninterface IERC1155Errors {\n    /**\n     * @dev Indicates an error related to the current `balance` of a `sender`. Used in transfers.\n     * @param sender Address whose tokens are being transferred.\n     * @param balance Current balance for the interacting account.\n     * @param needed Minimum amount required to perform a transfer.\n     * @param tokenId Identifier number of a token.\n     */\n    error ERC1155InsufficientBalance(address sender, uint256 balance, uint256 needed, uint256 tokenId);\n\n    /**\n     * @dev Indicates a failure with the token `sender`. Used in transfers.\n     * @param sender Address whose tokens are being transferred.\n     */\n    error ERC1155InvalidSender(address sender);\n\n    /**\n     * @dev Indicates a failure with the token `receiver`. Used in transfers.\n     * @param receiver Address to which tokens are being transferred.\n     */\n    error ERC1155InvalidReceiver(address receiver);\n\n    /**\n     * @dev Indicates a failure with the `operator`’s approval. Used in transfers.\n     * @param operator Address that may be allowed to operate on tokens without being their owner.\n     * @param owner Address of the current owner of a token.\n     */\n    error ERC1155MissingApprovalForAll(address operator, address owner);\n\n    /**\n     * @dev Indicates a failure with the `approver` of a token to be approved. Used in approvals.\n     * @param approver Address initiating an approval operation.\n     */\n    error ERC1155InvalidApprover(address approver);\n\n    /**\n     * @dev Indicates a failure with the `operator` to be approved. Used in approvals.\n     * @param operator Address that may be allowed to operate on tokens without being their owner.\n     */\n    error ERC1155InvalidOperator(address operator);\n\n    /**\n     * @dev Indicates an array length mismatch between ids and values in a safeBatchTransferFrom operation.\n     * Used in batch transfers.\n     * @param idsLength Length of the array of token identifiers\n     * @param valuesLength Length of the array of token amounts\n     */\n    error ERC1155InvalidArrayLength(uint256 idsLength, uint256 valuesLength);\n}"
			}
		}
	},
	"output": {
		"contracts": {
			"contracts/access_token/draft-IERC6093.sol": {
				"IERC1155Errors": {
					"abi": [
						{
							"inputs": [
								{
									"internalType": "address",
									"name": "sender",
									"type": "address"
								},
								{
									"internalType": "uint256",
									"name": "balance",
									"type": "uint256"
								},
								{
									"internalType": "uint256",
									"name": "needed",
									"type": "uint256"
								},
								{
									"internalType": "uint256",
									"name": "tokenId",
									"type": "uint256"
								}
							],
							"name": "ERC1155InsufficientBalance",
							"type": "error"
						},
						{
							"inputs": [
								{
									"internalType": "address",
									"name": "approver",
									"type": "address"
								}
							],
							"name": "ERC1155InvalidApprover",
							"type": "error"
						},
						{
							"inputs": [
								{
									"internalType": "uint256",
									"name": "idsLength",
									"type": "uint256"
								},
								{
									"internalType": "uint256",
									"name": "valuesLength",
									"type": "uint256"
								}
							],
							"name": "ERC1155InvalidArrayLength",
							"type": "error"
						},
						{
							"inputs": [
								{
									"internalType": "address",
									"name": "operator",
									"type": "address"
								}
							],
							"name": "ERC1155InvalidOperator",
							"type": "error"
						},
						{
							"inputs": [
								{
									"internalType": "address",
									"name": "receiver",
									"type": "address"
								}
							],
							"name": "ERC1155InvalidReceiver",
							"type": "error"
						},
						{
							"inputs": [
								{
									"internalType": "address",
									"name": "sender",
									"type": "address"
								}
							],
							"name": "ERC1155InvalidSender",
							"type": "error"
						},
						{
							"inputs": [
								{
									"internalType": "address",
									"name": "operator",
									"type": "address"
								},
								{
									"internalType": "address",
									"name": "owner",
									"type": "address"
								}
							],
							"name": "ERC1155MissingApprovalForAll",
							"type": "error"
						}
					],
					"devdoc": {
						"details": "Standard ERC1155 Errors Interface of the https://eips.ethereum.org/EIPS/eip-6093[ERC-6093] custom errors for ERC1155 tokens.",
						"errors": {
							"ERC1155InsufficientBalance(address,uint256,uint256,uint256)": [
								{
									"details": "Indicates an error related to the current `balance` of a `sender`. Used in transfers.",
									"params": {
										"balance": "Current balance for the interacting account.",
										"needed": "Minimum amount required to perform a transfer.",
										"sender": "Address whose tokens are being transferred.",
										"tokenId": "Identifier number of a token."
									}
								}
							],
							"ERC1155InvalidApprover(address)": [
								{
									"details": "Indicates a failure with the `approver` of a token to be approved. Used in approvals.",
									"params": {
										"approver": "Address initiating an approval operation."
									}
								}
							],
							"ERC1155InvalidArrayLength(uint256,uint256)": [
								{
									"details": "Indicates an array length mismatch between ids and values in a safeBatchTransferFrom operation. Used in batch transfers.",
									"params": {
										"idsLength": "Length of the array of token identifiers",
										"valuesLength": "Length of the array of token amounts"
									}
								}
							],
							"ERC1155InvalidOperator(address)": [
								{
									"details": "Indicates a failure with the `operator` to be approved. Used in approvals.",
									"params": {
										"operator": "Address that may be allowed to operate on tokens without being their owner."
									}
								}
							],
							"ERC1155InvalidReceiver(address)": [
								{
									"details": "Indicates a failure with the token `receiver`. Used in transfers.",
									"params": {
										"receiver": "Address to which tokens are being transferred."
									}
								}
							],
							"ERC1155InvalidSender(address)": [
								{
									"details": "Indicates a failure with the token `sender`. Used in transfers.",
									"params": {
										"sender": "Address whose tokens are being transferred."
									}
								}
							],
							"ERC1155MissingApprovalForAll(address,address)": [
								{
									"details": "Indicates a failure with the `operator`’s approval. Used in transfers.",
									"params": {
										"operator": "Address that may be allowed to operate on tokens without being their owner.",
										"owner": "Address of the current owner of a token."
									}
								}
							]
						},
						"kind": "dev",
						"methods": {},
						"version": 1
					},
					"evm": {
						"bytecode": {
							"functionDebugData": {},
							"generatedSources": [],
							"linkReferences": {},
							"object": "",
							"opcodes": "",
							"sourceMap": ""
						},
						"deployedBytecode": {
							"functionDebugData": {},
							"generatedSources": [],
							"immutableReferences": {},
							"linkReferences": {},
							"object": "",
							"opcodes": "",
							"sourceMap": ""
						}
					},
					"metadata": "{\"compiler\":{\"version\":\"0.8.23+commit.f704f362\"},\"language\":\"Solidity\",\"output\":{\"abi\":[{\"inputs\":[{\"internalType\":\"address\",\"name\":\"sender\",\"type\":\"address\"},{\"internalType\":\"uint256\",\"name\":\"balance\",\"type\":\"uint256\"},{\"internalType\":\"uint256\",\"name\":\"needed\",\"type\":\"uint256\"},{\"internalType\":\"uint256\",\"name\":\"tokenId\",\"type\":\"uint256\"}],\"name\":\"ERC1155InsufficientBalance\",\"type\":\"error\"},{\"inputs\":[{\"internalType\":\"address\",\"name\":\"approver\",\"type\":\"address\"}],\"name\":\"ERC1155InvalidApprover\",\"type\":\"error\"},{\"inputs\":[{\"internalType\":\"uint256\",\"name\":\"idsLength\",\"type\":\"uint256\"},{\"internalType\":\"uint256\",\"name\":\"valuesLength\",\"type\":\"uint256\"}],\"name\":\"ERC1155InvalidArrayLength\",\"type\":\"error\"},{\"inputs\":[{\"internalType\":\"address\",\"name\":\"operator\",\"type\":\"address\"}],\"name\":\"ERC1155InvalidOperator\",\"type\":\"error\"},{\"inputs\":[{\"internalType\":\"address\",\"name\":\"receiver\",\"type\":\"address\"}],\"name\":\"ERC1155InvalidReceiver\",\"type\":\"error\"},{\"inputs\":[{\"internalType\":\"address\",\"name\":\"sender\",\"type\":\"address\"}],\"name\":\"ERC1155InvalidSender\",\"type\":\"error\"},{\"inputs\":[{\"internalType\":\"address\",\"name\":\"operator\",\"type\":\"address\"},{\"internalType\":\"address\",\"name\":\"owner\",\"type\":\"address\"}],\"name\":\"ERC1155MissingApprovalForAll\",\"type\":\"error\"}],\"devdoc\":{\"details\":\"Standard ERC1155 Errors Interface of the https://eips.ethereum.org/EIPS/eip-6093[ERC-6093] custom errors for ERC1155 tokens.\",\"errors\":{\"ERC1155InsufficientBalance(address,uint256,uint256,uint256)\":[{\"details\":\"Indicates an error related to the current `balance` of a `sender`. Used in transfers.\",\"params\":{\"balance\":\"Current balance for the interacting account.\",\"needed\":\"Minimum amount required to perform a transfer.\",\"sender\":\"Address whose tokens are being transferred.\",\"tokenId\":\"Identifier number of a token.\"}}],\"ERC1155InvalidApprover(address)\":[{\"details\":\"Indicates a failure with the `approver` of a token to be approved. Used in approvals.\",\"params\":{\"approver\":\"Address initiating an approval operation.\"}}],\"ERC1155InvalidArrayLength(uint256,uint256)\":[{\"details\":\"Indicates an array length mismatch between ids and values in a safeBatchTransferFrom operation. Used in batch transfers.\",\"params\":{\"idsLength\":\"Length of the array of token identifiers\",\"valuesLength\":\"Length of the array of token amounts\"}}],\"ERC1155InvalidOperator(address)\":[{\"details\":\"Indicates a failure with the `operator` to be approved. Used in approvals.\",\"params\":{\"operator\":\"Address that may be allowed to operate on tokens without being their owner.\"}}],\"ERC1155InvalidReceiver(address)\":[{\"details\":\"Indicates a failure with the token `receiver`. Used in transfers.\",\"params\":{\"receiver\":\"Address to which tokens are being transferred.\"}}],\"ERC1155InvalidSender(address)\":[{\"details\":\"Indicates a failure with the token `sender`. Used in transfers.\",\"params\":{\"sender\":\"Address whose tokens are being transferred.\"}}],\"ERC1155MissingApprovalForAll(address,address)\":[{\"details\":\"Indicates a failure with the `operator`\\u2019s approval. Used in transfers.\",\"params\":{\"operator\":\"Address that may be allowed to operate on tokens without being their owner.\",\"owner\":\"Address of the current owner of a token.\"}}]},\"kind\":\"dev\",\"methods\":{},\"version\":1},\"userdoc\":{\"kind\":\"user\",\"methods\":{},\"version\":1}},\"settings\":{\"compilationTarget\":{\"contracts/access_token/draft-IERC6093.sol\":\"IERC1155Errors\"},\"evmVersion\":\"shanghai\",\"libraries\":{},\"metadata\":{\"bytecodeHash\":\"ipfs\"},\"optimizer\":{\"enabled\":true,\"runs\":200},\"remappings\":[],\"viaIR\":true},\"sources\":{\"contracts/access_token/draft-IERC6093.sol\":{\"keccak256\":\"0x68997d3147926564cee6f3558c252378207a792ffcd058047dacc3afa2a1e309\",\"license\":\"MIT\",\"urls\":[\"bzz-raw://00cc413a013f20cecd3f4d5012b0fbad31cfcbbd1767a22d738bbc09093ed7a8\",\"dweb:/ipfs/QmYKxXCfpES4sLCk4uGT9KZ1m5vL7pidw72RmoAFTQy7Xw\"]}},\"version\":1}",
					"userdoc": {
						"kind": "user",
						"methods": {},
						"version": 1
					}
				},
				"IERC20Errors": {
					"abi": [
						{
							"inputs": [
								{
									"internalType": "address",
									"name": "spender",
									"type": "address"
								},
								{
									"internalType": "uint256",
									"name": "allowance",
									"type": "uint256"
								},
								{
									"internalType": "uint256",
									"name": "needed",
									"type": "uint256"
								}
							],
							"name": "ERC20InsufficientAllowance",
							"type": "error"
						},
						{
							"inputs": [
								{
									"internalType": "address",
									"name": "sender",
									"type": "address"
								},
								{
									"internalType": "uint256",
									"name": "balance",
									"type": "uint256"
								},
								{
									"internalType": "uint256",
									"name": "needed",
									"type": "uint256"
								}
							],
							"name": "ERC20InsufficientBalance",
							"type": "error"
						},
						{
							"inputs": [
								{
									"internalType": "address",
									"name": "approver",
									"type": "address"
								}
							],
							"name": "ERC20InvalidApprover",
							"type": "error"
						},
						{
							"inputs": [
								{
									"internalType": "address",
									"name": "receiver",
									"type": "address"
								}
							],
							"name": "ERC20InvalidReceiver",
							"type": "error"
						},
						{
							"inputs": [
								{
									"internalType": "address",
									"name": "sender",
									"type": "address"
								}
							],
							"name": "ERC20InvalidSender",
							"type": "error"
						},
						{
							"inputs": [
								{
									"internalType": "address",
									"name": "spender",
									"type": "address"
								}
							],
							"name": "ERC20InvalidSpender",
							"type": "error"
						}
					],
					"devdoc": {
						"details": "Standard ERC20 Errors Interface of the https://eips.ethereum.org/EIPS/eip-6093[ERC-6093] custom errors for ERC20 tokens.",
						"errors": {
							"ERC20InsufficientAllowance(address,uint256,uint256)": [
								{
									"details": "Indicates a failure with the `spender`’s `allowance`. Used in transfers.",
									"params": {
										"allowance": "Amount of tokens a `spender` is allowed to operate with.",
										"needed": "Minimum amount required to perform a transfer.",
										"spender": "Address that may be allowed to operate on tokens without being their owner."
									}
								}
							],
							"ERC20InsufficientBalance(address,uint256,uint256)": [
								{
									"details": "Indicates an error related to the current `balance` of a `sender`. Used in transfers.",
									"params": {
										"balance": "Current balance for the interacting account.",
										"needed": "Minimum amount required to perform a transfer.",
										"sender": "Address whose tokens are being transferred."
									}
								}
							],
							"ERC20InvalidApprover(address)": [
								{
									"details": "Indicates a failure with the `approver` of a token to be approved. Used in approvals.",
									"params": {
										"approver": "Address initiating an approval operation."
									}
								}
							],
							"ERC20InvalidReceiver(address)": [
								{
									"details": "Indicates a failure with the token `receiver`. Used in transfers.",
									"params": {
										"receiver": "Address to which tokens are being transferred."
									}
								}
							],
							"ERC20InvalidSender(address)": [
								{
									"details": "Indicates a failure with the token `sender`. Used in transfers.",
									"params": {
										"sender": "Address whose tokens are being transferred."
									}
								}
							],
							"ERC20InvalidSpender(address)": [
								{
									"details": "Indicates a failure with the `spender` to be approved. Used in approvals.",
									"params": {
										"spender": "Address that may be allowed to operate on tokens without being their owner."
									}
								}
							]
						},
						"kind": "dev",
						"methods": {},
						"version": 1
					},
					"evm": {
						"bytecode": {
							"functionDebugData": {},
							"generatedSources": [],
							"linkReferences": {},
							"object": "",
							"opcodes": "",
							"sourceMap": ""
						},
						"deployedBytecode": {
							"functionDebugData": {},
							"generatedSources": [],
							"immutableReferences": {},
							"linkReferences": {},
							"object": "",
							"opcodes": "",
							"sourceMap": ""
						}
					},
					"metadata": "{\"compiler\":{\"version\":\"0.8.23+commit.f704f362\"},\"language\":\"Solidity\",\"output\":{\"abi\":[{\"inputs\":[{\"internalType\":\"address\",\"name\":\"spender\",\"type\":\"address\"},{\"internalType\":\"uint256\",\"name\":\"allowance\",\"type\":\"uint256\"},{\"internalType\":\"uint256\",\"name\":\"needed\",\"type\":\"uint256\"}],\"name\":\"ERC20InsufficientAllowance\",\"type\":\"error\"},{\"inputs\":[{\"internalType\":\"address\",\"name\":\"sender\",\"type\":\"address\"},{\"internalType\":\"uint256\",\"name\":\"balance\",\"type\":\"uint256\"},{\"internalType\":\"uint256\",\"name\":\"needed\",\"type\":\"uint256\"}],\"name\":\"ERC20InsufficientBalance\",\"type\":\"error\"},{\"inputs\":[{\"internalType\":\"address\",\"name\":\"approver\",\"type\":\"address\"}],\"name\":\"ERC20InvalidApprover\",\"type\":\"error\"},{\"inputs\":[{\"internalType\":\"address\",\"name\":\"receiver\",\"type\":\"address\"}],\"name\":\"ERC20InvalidReceiver\",\"type\":\"error\"},{\"inputs\":[{\"internalType\":\"address\",\"name\":\"sender\",\"type\":\"address\"}],\"name\":\"ERC20InvalidSender\",\"type\":\"error\"},{\"inputs\":[{\"internalType\":\"address\",\"name\":\"spender\",\"type\":\"address\"}],\"name\":\"ERC20InvalidSpender\",\"type\":\"error\"}],\"devdoc\":{\"details\":\"Standard ERC20 Errors Interface of the https://eips.ethereum.org/EIPS/eip-6093[ERC-6093] custom errors for ERC20 tokens.\",\"errors\":{\"ERC20InsufficientAllowance(address,uint256,uint256)\":[{\"details\":\"Indicates a failure with the `spender`\\u2019s `allowance`. Used in transfers.\",\"params\":{\"allowance\":\"Amount of tokens a `spender` is allowed to operate with.\",\"needed\":\"Minimum amount required to perform a transfer.\",\"spender\":\"Address that may be allowed to operate on tokens without being their owner.\"}}],\"ERC20InsufficientBalance(address,uint256,uint256)\":[{\"details\":\"Indicates an error related to the current `balance` of a `sender`. Used in transfers.\",\"params\":{\"balance\":\"Current balance for the interacting account.\",\"needed\":\"Minimum amount required to perform a transfer.\",\"sender\":\"Address whose tokens are being transferred.\"}}],\"ERC20InvalidApprover(address)\":[{\"details\":\"Indicates a failure with the `approver` of a token to be approved. Used in approvals.\",\"params\":{\"approver\":\"Address initiating an approval operation.\"}}],\"ERC20InvalidReceiver(address)\":[{\"details\":\"Indicates a failure with the token `receiver`. Used in transfers.\",\"params\":{\"receiver\":\"Address to which tokens are being transferred.\"}}],\"ERC20InvalidSender(address)\":[{\"details\":\"Indicates a failure with the token `sender`. Used in transfers.\",\"params\":{\"sender\":\"Address whose tokens are being transferred.\"}}],\"ERC20InvalidSpender(address)\":[{\"details\":\"Indicates a failure with the `spender` to be approved. Used in approvals.\",\"params\":{\"spender\":\"Address that may be allowed to operate on tokens without being their owner.\"}}]},\"kind\":\"dev\",\"methods\":{},\"version\":1},\"userdoc\":{\"kind\":\"user\",\"methods\":{},\"version\":1}},\"settings\":{\"compilationTarget\":{\"contracts/access_token/draft-IERC6093.sol\":\"IERC20Errors\"},\"evmVersion\":\"shanghai\",\"libraries\":{},\"metadata\":{\"bytecodeHash\":\"ipfs\"},\"optimizer\":{\"enabled\":true,\"runs\":200},\"remappings\":[],\"viaIR\":true},\"sources\":{\"contracts/access_token/draft-IERC6093.sol\":{\"keccak256\":\"0x68997d3147926564cee6f3558c252378207a792ffcd058047dacc3afa2a1e309\",\"license\":\"MIT\",\"urls\":[\"bzz-raw://00cc413a013f20cecd3f4d5012b0fbad31cfcbbd1767a22d738bbc09093ed7a8\",\"dweb:/ipfs/QmYKxXCfpES4sLCk4uGT9KZ1m5vL7pidw72RmoAFTQy7Xw\"]}},\"version\":1}",
					"userdoc": {
						"kind": "user",
						"methods": {},
						"version": 1
					}
				},
				"IERC721Errors": {
					"abi": [
						{
							"inputs": [
								{
									"internalType": "address",
									"name": "sender",
									"type": "address"
								},
								{
									"internalType": "uint256",
									"name": "tokenId",
									"type": "uint256"
								},
								{
									"internalType": "address",
									"name": "owner",
									"type": "address"
								}
							],
							"name": "ERC721IncorrectOwner",
							"type": "error"
						},
						{
							"inputs": [
								{
									"internalType": "address",
									"name": "operator",
									"type": "address"
								},
								{
									"internalType": "uint256",
									"name": "tokenId",
									"type": "uint256"
								}
							],
							"name": "ERC721InsufficientApproval",
							"type": "error"
						},
						{
							"inputs": [
								{
									"internalType": "address",
									"name": "approver",
									"type": "address"
								}
							],
							"name": "ERC721InvalidApprover",
							"type": "error"
						},
						{
							"inputs": [
								{
									"internalType": "address",
									"name": "operator",
									"type": "address"
								}
							],
							"name": "ERC721InvalidOperator",
							"type": "error"
						},
						{
							"inputs": [
								{
									"internalType": "address",
									"name": "owner",
									"type": "address"
								}
							],
							"name": "ERC721InvalidOwner",
							"type": "error"
						},
						{
							"inputs": [
								{
									"internalType": "address",
									"name": "receiver",
									"type": "address"
								}
							],
							"name": "ERC721InvalidReceiver",
							"type": "error"
						},
						{
							"inputs": [
								{
									"internalType": "address",
									"name": "sender",
									"type": "address"
								}
							],
							"name": "ERC721InvalidSender",
							"type": "error"
						},
						{
							"inputs": [
								{
									"internalType": "uint256",
									"name": "tokenId",
									"type": "uint256"
								}
							],
							"name": "ERC721NonexistentToken",
							"type": "error"
						}
					],
					"devdoc": {
						"details": "Standard ERC721 Errors Interface of the https://eips.ethereum.org/EIPS/eip-6093[ERC-6093] custom errors for ERC721 tokens.",
						"errors": {
							"ERC721IncorrectOwner(address,uint256,address)": [
								{
									"details": "Indicates an error related to the ownership over a particular token. Used in transfers.",
									"params": {
										"owner": "Address of the current owner of a token.",
										"sender": "Address whose tokens are being transferred.",
										"tokenId": "Identifier number of a token."
									}
								}
							],
							"ERC721InsufficientApproval(address,uint256)": [
								{
									"details": "Indicates a failure with the `operator`’s approval. Used in transfers.",
									"params": {
										"operator": "Address that may be allowed to operate on tokens without being their owner.",
										"tokenId": "Identifier number of a token."
									}
								}
							],
							"ERC721InvalidApprover(address)": [
								{
									"details": "Indicates a failure with the `approver` of a token to be approved. Used in approvals.",
									"params": {
										"approver": "Address initiating an approval operation."
									}
								}
							],
							"ERC721InvalidOperator(address)": [
								{
									"details": "Indicates a failure with the `operator` to be approved. Used in approvals.",
									"params": {
										"operator": "Address that may be allowed to operate on tokens without being their owner."
									}
								}
							],
							"ERC721InvalidOwner(address)": [
								{
									"details": "Indicates that an address can't be an owner. For example, `address(0)` is a forbidden owner in EIP-20. Used in balance queries.",
									"params": {
										"owner": "Address of the current owner of a token."
									}
								}
							],
							"ERC721InvalidReceiver(address)": [
								{
									"details": "Indicates a failure with the token `receiver`. Used in transfers.",
									"params": {
										"receiver": "Address to which tokens are being transferred."
									}
								}
							],
							"ERC721InvalidSender(address)": [
								{
									"details": "Indicates a failure with the token `sender`. Used in transfers.",
									"params": {
										"sender": "Address whose tokens are being transferred."
									}
								}
							],
							"ERC721NonexistentToken(uint256)": [
								{
									"details": "Indicates a `tokenId` whose `owner` is the zero address.",
									"params": {
										"tokenId": "Identifier number of a token."
									}
								}
							]
						},
						"kind": "dev",
						"methods": {},
						"version": 1
					},
					"evm": {
						"bytecode": {
							"functionDebugData": {},
							"generatedSources": [],
							"linkReferences": {},
							"object": "",
							"opcodes": "",
							"sourceMap": ""
						},
						"deployedBytecode": {
							"functionDebugData": {},
							"generatedSources": [],
							"immutableReferences": {},
							"linkReferences": {},
							"object": "",
							"opcodes": "",
							"sourceMap": ""
						}
					},
					"metadata": "{\"compiler\":{\"version\":\"0.8.23+commit.f704f362\"},\"language\":\"Solidity\",\"output\":{\"abi\":[{\"inputs\":[{\"internalType\":\"address\",\"name\":\"sender\",\"type\":\"address\"},{\"internalType\":\"uint256\",\"name\":\"tokenId\",\"type\":\"uint256\"},{\"internalType\":\"address\",\"name\":\"owner\",\"type\":\"address\"}],\"name\":\"ERC721IncorrectOwner\",\"type\":\"error\"},{\"inputs\":[{\"internalType\":\"address\",\"name\":\"operator\",\"type\":\"address\"},{\"internalType\":\"uint256\",\"name\":\"tokenId\",\"type\":\"uint256\"}],\"name\":\"ERC721InsufficientApproval\",\"type\":\"error\"},{\"inputs\":[{\"internalType\":\"address\",\"name\":\"approver\",\"type\":\"address\"}],\"name\":\"ERC721InvalidApprover\",\"type\":\"error\"},{\"inputs\":[{\"internalType\":\"address\",\"name\":\"operator\",\"type\":\"address\"}],\"name\":\"ERC721InvalidOperator\",\"type\":\"error\"},{\"inputs\":[{\"internalType\":\"address\",\"name\":\"owner\",\"type\":\"address\"}],\"name\":\"ERC721InvalidOwner\",\"type\":\"error\"},{\"inputs\":[{\"internalType\":\"address\",\"name\":\"receiver\",\"type\":\"address\"}],\"name\":\"ERC721InvalidReceiver\",\"type\":\"error\"},{\"inputs\":[{\"internalType\":\"address\",\"name\":\"sender\",\"type\":\"address\"}],\"name\":\"ERC721InvalidSender\",\"type\":\"error\"},{\"inputs\":[{\"internalType\":\"uint256\",\"name\":\"tokenId\",\"type\":\"uint256\"}],\"name\":\"ERC721NonexistentToken\",\"type\":\"error\"}],\"devdoc\":{\"details\":\"Standard ERC721 Errors Interface of the https://eips.ethereum.org/EIPS/eip-6093[ERC-6093] custom errors for ERC721 tokens.\",\"errors\":{\"ERC721IncorrectOwner(address,uint256,address)\":[{\"details\":\"Indicates an error related to the ownership over a particular token. Used in transfers.\",\"params\":{\"owner\":\"Address of the current owner of a token.\",\"sender\":\"Address whose tokens are being transferred.\",\"tokenId\":\"Identifier number of a token.\"}}],\"ERC721InsufficientApproval(address,uint256)\":[{\"details\":\"Indicates a failure with the `operator`\\u2019s approval. Used in transfers.\",\"params\":{\"operator\":\"Address that may be allowed to operate on tokens without being their owner.\",\"tokenId\":\"Identifier number of a token.\"}}],\"ERC721InvalidApprover(address)\":[{\"details\":\"Indicates a failure with the `approver` of a token to be approved. Used in approvals.\",\"params\":{\"approver\":\"Address initiating an approval operation.\"}}],\"ERC721InvalidOperator(address)\":[{\"details\":\"Indicates a failure with the `operator` to be approved. Used in approvals.\",\"params\":{\"operator\":\"Address that may be allowed to operate on tokens without being their owner.\"}}],\"ERC721InvalidOwner(address)\":[{\"details\":\"Indicates that an address can't be an owner. For example, `address(0)` is a forbidden owner in EIP-20. Used in balance queries.\",\"params\":{\"owner\":\"Address of the current owner of a token.\"}}],\"ERC721InvalidReceiver(address)\":[{\"details\":\"Indicates a failure with the token `receiver`. Used in transfers.\",\"params\":{\"receiver\":\"Address to which tokens are being transferred.\"}}],\"ERC721InvalidSender(address)\":[{\"details\":\"Indicates a failure with the token `sender`. Used in transfers.\",\"params\":{\"sender\":\"Address whose tokens are being transferred.\"}}],\"ERC721NonexistentToken(uint256)\":[{\"details\":\"Indicates a `tokenId` whose `owner` is the zero address.\",\"params\":{\"tokenId\":\"Identifier number of a token.\"}}]},\"kind\":\"dev\",\"methods\":{},\"version\":1},\"userdoc\":{\"kind\":\"user\",\"methods\":{},\"version\":1}},\"settings\":{\"compilationTarget\":{\"contracts/access_token/draft-IERC6093.sol\":\"IERC721Errors\"},\"evmVersion\":\"shanghai\",\"libraries\":{},\"metadata\":{\"bytecodeHash\":\"ipfs\"},\"optimizer\":{\"enabled\":true,\"runs\":200},\"remappings\":[],\"viaIR\":true},\"sources\":{\"contracts/access_token/draft-IERC6093.sol\":{\"keccak256\":\"0x68997d3147926564cee6f3558c252378207a792ffcd058047dacc3afa2a1e309\",\"license\":\"MIT\",\"urls\":[\"bzz-raw://00cc413a013f20cecd3f4d5012b0fbad31cfcbbd1767a22d738bbc09093ed7a8\",\"dweb:/ipfs/QmYKxXCfpES4sLCk4uGT9KZ1m5vL7pidw72RmoAFTQy7Xw\"]}},\"version\":1}",
					"userdoc": {
						"kind": "user",
						"methods": {},
						"version": 1
					}
				}
			}
		},
		"sources": {
			"contracts/access_token/draft-IERC6093.sol": {
				"id": 0
			}
		}
	}
}